LICENSE
MANIFEST.in
README.md
setup.py
punter/__init__.py
punter/api.py
punter/exceptions.py
punter/helpers.py
punter.egg-info/PKG-INFO
punter.egg-info/SOURCES.txt
punter.egg-info/dependency_links.txt
punter.egg-info/pbr.json
punter.egg-info/requires.txt
punter.egg-info/top_level.txt