Metadata-Version: 1.1
Name: punter
Version: 0.1.2
Summary: Python wrapper for the Email Hunter API
Home-page: https://github.com/jgoodlet/punter
Author: Joshua Goodlett
Author-email: joshuagoodlett@gmail.com
License: MIT
Platform: UNKNOWN
Classifier: Development Status :: 3 - Alpha
Classifier: Intended Audience :: Developers
Classifier: Natural Language :: English
Classifier: License :: OSI Approved :: MIT License
Classifier: Programming Language :: Python
Classifier: Programming Language :: Python :: 2.6
Classifier: Programming Language :: Python :: 2.7
Classifier: Programming Language :: Python :: 3
Classifier: Programming Language :: Python :: 3.3
Classifier: Programming Language :: Python :: 3.4
